{
  "listing_id": 3303643,
  "id": 27372343,
  "date": "2015-03-02",
  "reviewer_id": 25718998,
  "reviewer_name": "Dale",
  "text": "Our first experience with airbnb and was great.  Lisa's small, quiet space was perfect for a weekend visit with our son, daughter-in-law and new grand baby just a few blocks away.  Wish the weather would have allowed us to spend time on the deck with a glass of wine.  Thanks Lisa!",
  "title": "Zilker apartment-great spot!",
  "host_id": 9906097,
  "listing_latitude": 30.254229833866017,
  "listing_longitude": -97.77281040930032,
  "host_name": "Lisa"
}
