{
  "listing_id": 347802,
  "id": 1723481,
  "date": "2012-07-16",
  "reviewer_id": 2749794,
  "reviewer_name": "Alejandro",
  "text": "The house was perfect for us. Very clean and in a great location.\r\nThe decoration is simple and functional. I have stayed in some rental properties in Austin and this is, by far, the best of all. We will definitely come back to this house.",
  "title": "Hyde Park Bungalow close to UT & DT",
  "host_id": 1594787,
  "listing_latitude": 30.30229498844927,
  "listing_longitude": -97.7281497793535,
  "host_name": "Ananda & Dunstan"
}
