{
  "listing_id": 2266768,
  "id": 29729261,
  "date": "2015-04-12",
  "reviewer_id": 7236482,
  "reviewer_name": "J.R.",
  "text": "This space was absolutely beautiful. The shower may have been the highlight of the entire trip to Austin. Kristine and her family allowed it to feel like you were in your own apartment with the incredible amount of privacy.",
  "title": "modern granny flat",
  "host_id": 1507234,
  "listing_latitude": 30.275484886441834,
  "listing_longitude": -97.726282028393,
  "host_name": "Kristine"
}
