{
  "listing_id": 8421657,
  "id": 52759159,
  "date": "2015-11-01",
  "reviewer_id": 46236518,
  "reviewer_name": "Kristin",
  "text": "The space what a great amount of room and space. The Lyft trip was close to downtown and about the price in the listing. Check in was a breeze since Taylor arranged key pickup, which was nice. The airbnb listing didn't provide the direct location, which caused a bit of confusion prior to check in the day of, the address and map were two different locations. After a direct text to Taylor that was quickly resolved.",
  "title": "Cozy Space Close to City",
  "host_id": 22819430,
  "listing_latitude": 30.22767879283835,
  "listing_longitude": -97.74140832917367,
  "host_name": "Taylor"
}
