{
  "listing_id": 5538509,
  "id": 28046905,
  "date": "2015-03-16",
  "reviewer_id": 19311356,
  "reviewer_name": "Nik",
  "text": "Yolanda and Mike were great. I didn't see much of them since I was so busy and out late at SXSW, but they are very accommodating and kind, and I only have good things to say about stay. The house is also really close to a bus stop which takes you right downtown, which was great.",
  "title": "1 bedroom in Central Austin",
  "host_id": 5927859,
  "listing_latitude": 30.321567265962315,
  "listing_longitude": -97.71743286409021,
  "host_name": "Yolanda"
}
