{
  "listing_id": 7679,
  "id": 30836,
  "date": "2010-03-22",
  "reviewer_id": 87383,
  "reviewer_name": "Chantal",
  "text": "Courtney and Joep are very nice hosts. The breakfast buffet was fabulous, with everything needed, including fresh fruits and organic cereals, and a cappuccino-machine! The house is located in a quite and very green neighborhood.",
  "title": "North Austin garden haven",
  "host_id": 17333,
  "listing_latitude": 30.383545215797866,
  "listing_longitude": -97.66676146218637,
  "host_name": "Joep And Courtney"
}
